webexteamssdk/__init__.py
webexteamssdk/_metadata.py
webexteamssdk/_version.py
webexteamssdk/config.py
webexteamssdk/environment.py
webexteamssdk/exceptions.py
webexteamssdk/generator_containers.py
webexteamssdk/response_codes.py
webexteamssdk/restsession.py
webexteamssdk/utils.py
webexteamssdk/api/__init__.py
webexteamssdk/api/access_tokens.py
webexteamssdk/api/admin_audit_events.py
webexteamssdk/api/attachment_actions.py
webexteamssdk/api/events.py
webexteamssdk/api/guest_issuer.py
webexteamssdk/api/licenses.py
webexteamssdk/api/memberships.py
webexteamssdk/api/messages.py
webexteamssdk/api/organizations.py
webexteamssdk/api/people.py
webexteamssdk/api/roles.py
webexteamssdk/api/rooms.py
webexteamssdk/api/team_memberships.py
webexteamssdk/api/teams.py
webexteamssdk/api/webhooks.py
webexteamssdk/models/__init__.py
webexteamssdk/models/dictionary.py
webexteamssdk/models/immutable.py
webexteamssdk/models/simple.py
webexteamssdk/models/cards/__init__.py
webexteamssdk/models/cards/actions.py
webexteamssdk/models/cards/adaptive_card_component.py
webexteamssdk/models/cards/card.py
webexteamssdk/models/cards/components.py
webexteamssdk/models/cards/container.py
webexteamssdk/models/cards/inputs.py
webexteamssdk/models/cards/options.py
webexteamssdk/models/cards/utils.py
webexteamssdk/models/mixins/__init__.py
webexteamssdk/models/mixins/access_token.py
webexteamssdk/models/mixins/admin_audit_event.py
webexteamssdk/models/mixins/attachment_action.py
webexteamssdk/models/mixins/event.py
webexteamssdk/models/mixins/guest_issuer_token.py
webexteamssdk/models/mixins/license.py
webexteamssdk/models/mixins/membership.py
webexteamssdk/models/mixins/message.py
webexteamssdk/models/mixins/organization.py
webexteamssdk/models/mixins/person.py
webexteamssdk/models/mixins/role.py
webexteamssdk/models/mixins/room.py
webexteamssdk/models/mixins/room_meeting_info.py
webexteamssdk/models/mixins/team.py
webexteamssdk/models/mixins/team_membership.py
webexteamssdk/models/mixins/webhook.py
webexteamssdk-1.6.1.dist-info/LICENSE
webexteamssdk-1.6.1.dist-info/METADATA
webexteamssdk-1.6.1.dist-info/WHEEL
webexteamssdk-1.6.1.dist-info/top_level.txt
webexteamssdk-1.6.1.dist-info/RECORD
